helloworld.py
helloworldrm-0.0.1.dist-info/DESCRIPTION.rst
helloworldrm-0.0.1.dist-info/METADATA
helloworldrm-0.0.1.dist-info/RECORD
helloworldrm-0.0.1.dist-info/WHEEL
helloworldrm-0.0.1.dist-info/metadata.json
helloworldrm-0.0.1.dist-info/top_level.txt
